east/__init__.py
east/__main__.py
east/configuration-schema.yaml
east/constants.py
east/east_context.py
east/east_yml.py
east/helper_functions.py
east/modules/artifact.py
east/modules/artifacts2pack.py
east/modules/parsedtag.py
east/modules/tsuite.py
east/modules/zephyr_semver.py
east/system_commands/__init__.py
east/system_commands/basic_west_commands.py
east/system_commands/install.py
east/system_commands/jlink_commands.py
east/system_commands/tooling.py
east/workspace_commands/__init__.py
east/workspace_commands/basic_commands.py
east/workspace_commands/build_type_flag.py
east/workspace_commands/codechecker_commands.py
east/workspace_commands/codechecker_helpers.py
east/workspace_commands/cortex_commands.py
east/workspace_commands/pack_commands.py
east/workspace_commands/release_commands.py
east/workspace_commands/update_commands.py
east/workspace_commands/version_commands.py
east_tool-0.29.6.dist-info/licenses/LICENSE
east_tool-0.29.6.dist-info/METADATA
east_tool-0.29.6.dist-info/WHEEL
east_tool-0.29.6.dist-info/entry_points.txt
east_tool-0.29.6.dist-info/top_level.txt
east_tool-0.29.6.dist-info/RECORD
