Metadata-Version: 2.4
Name: east-tool
Version: 0.29.6
Summary: Tool built on top of West for managing nRF Connect SDK projects.
Author-email: Marko Sagadin <marko.sagadin42@gmail.com>
License: MIT License
Project-URL: Homepage, https://github.com/IRNAS/irnas-east-software
Classifier: License :: OSI Approved :: MIT License
Classifier: Programming Language :: Python :: 3
Requires-Python: >=3.10
License-File: LICENSE
Requires-Dist: rich>=13.9.0
Requires-Dist: click>=8.0
Requires-Dist: rich_click>=1.8
Requires-Dist: requests>=2.32
Requires-Dist: PyYAML>=6.0.0
Requires-Dist: pykwalify==1.8.0
Requires-Dist: ansi2txt==0.2.0
Requires-Dist: portalocker
Requires-Dist: psutil
Provides-Extra: dev
Requires-Dist: ruff==0.6.0; extra == "dev"
Requires-Dist: pytest==8.3.2; extra == "dev"
Requires-Dist: pytest-mock==3.14.0; extra == "dev"
Requires-Dist: build==1.2.1; extra == "dev"
Requires-Dist: twine==5.1.1; extra == "dev"
Requires-Dist: setuptools_scm==8.1.0; extra == "dev"
Requires-Dist: tox==4.18.0; extra == "dev"
Dynamic: license-file
